{
  "project_info": {
    "project_number": "427126638951",
    "project_id": "game-39b8e",
    "storage_bucket": "game-39b8e.firebasestorage.app"
  },
  "client": [
    {
      "client_info": {
        "mobilesdk_app_id": "1:427126638951:android:7f138cea9e7f3cefca47c2",
        "android_client_info": {
          "package_name": "com.SmashLive.game_app"
        }
      },
      "oauth_client": [
        {
          "client_id": "427126638951-4dlpk3j6rn35j5fid70pofcbo8b68h6l.apps.googleusercontent.com",
          "client_type": 1,
          "android_info": {
            "package_name": "com.SmashLive.game_app",
            "certificate_hash": "38eb2d97fcb707e9526ee27c33343c6ba2df7904"
          }
        },
        {
          "client_id": "427126638951-3ofv1odq0e660lge9n2f8n8de8uj4u69.apps.googleusercontent.com",
          "client_type": 3
        }
      ],
      "api_key": [
        {
          "current_key": "AIzaSyDMPRkvSHRjQSxOirhf2Az0KZuFdtZfB5U"
        }
      ],
      "services": {
        "appinvite_service": {
          "other_platform_oauth_client": [
            {
              "client_id": "427126638951-3ofv1odq0e660lge9n2f8n8de8uj4u69.apps.googleusercontent.com",
              "client_type": 3
            },
            {
              "client_id": "427126638951-es7icvgb93edbfjfv1cucbd8b2rqmpc7.apps.googleusercontent.com",
              "client_type": 2,
              "ios_info": {
                "bundle_id": "com.smashlive.gameapp"
              }
            }
          ]
        }
      }
    },
    {
      "client_info": {
        "mobilesdk_app_id": "1:427126638951:android:e6be474e4cff7558ca47c2",
        "android_client_info": {
          "package_name": "com.smashlive.gameapp"
        }
      },
      "oauth_client": [
        {
          "client_id": "427126638951-3ofv1odq0e660lge9n2f8n8de8uj4u69.apps.googleusercontent.com",
          "client_type": 3
        }
      ],
      "api_key": [
        {
          "current_key": "AIzaSyDMPRkvSHRjQSxOirhf2Az0KZuFdtZfB5U"
        }
      ],
      "services": {
        "appinvite_service": {
          "other_platform_oauth_client": [
            {
              "client_id": "427126638951-3ofv1odq0e660lge9n2f8n8de8uj4u69.apps.googleusercontent.com",
              "client_type": 3
            },
            {
              "client_id": "427126638951-es7icvgb93edbfjfv1cucbd8b2rqmpc7.apps.googleusercontent.com",
              "client_type": 2,
              "ios_info": {
                "bundle_id": "com.smashlive.gameapp"
              }
            }
          ]
        }
      }
    }
  ],
  "configuration_version": "1"
}